cos_uploader/__init__.py
cos_uploader/common.py
cos_uploader/config.toml
cos_uploader/history.py
cos_uploader/install.py
cos_uploader-2.0.0rc3.dist-info/LICENSE
cos_uploader-2.0.0rc3.dist-info/METADATA
cos_uploader-2.0.0rc3.dist-info/WHEEL
cos_uploader-2.0.0rc3.dist-info/entry_points.txt
cos_uploader-2.0.0rc3.dist-info/RECORD
