Metadata-Version: 2.1
Name: cos-uploader
Version: 2.0.0rc3
Summary: CLI tool for uploading files to Tencent COS
Home-page: https://github.com/baobao1270/cos-uploader
License: MIT
Keywords: tencent-cos,uploader
Author: Joseph Chris
Author-email: joseph@josephcz.xyz
Requires-Python: >=3.8,<4.0
Classifier: License :: OSI Approved :: MIT License
Classifier: Programming Language :: Python :: 3
Classifier: Programming Language :: Python :: 3.8
Classifier: Programming Language :: Python :: 3.9
Classifier: Programming Language :: Python :: 3.10
Classifier: Programming Language :: Python :: 3.11
Requires-Dist: cos-python-sdk-v5 (>=1.9.24,<2.0.0)
Requires-Dist: toml (>=0.10.2,<0.11.0)
Project-URL: Documentation, https://github.com/baobao1270/cos-uploader/blob/main/README.md
Project-URL: Repository, https://github.com/baobao1270/cos-uploader.git
